[
  {
    "category": "postres",
    "pages": [1, 2, 3, 4, 5, 6, 7, 8, 9, 10, 11, 12, 13, 14, 15, 16, 17, 18]
  },
  { "category": "pasta", "pages": [1, 2, 3, 4, 5, 6, 7, 8, 9, 10] },
  { "category": "arroz", "pages": [1, 2, 3, 4, 5, 6, 7, 8, 9] },
  { "category": "pollo", "pages": [1, 2, 3, 4, 5, 6, 7, 8, 9, 10, 11, 12, 13] },
  { "category": "sopas-caldos", "pages": [1, 2, 3, 4] },
  { "category": "bizcochos", "pages": [1, 2, 3] },
  {
    "category": "carne",
    "pages": [
      1, 2, 3, 4, 5, 6, 7, 8, 9, 10, 11, 12, 13, 14, 15, 16, 17, 18, 19, 20, 21,
      22, 23
    ]
  },
  { "category": "guisos", "pages": [1, 2, 3, 4, 5, 6, 7, 8, 9, 10, 11, 12] },
  { "category": "legumbres", "pages": [1, 2, 3, 4, 5, 6, 7, 8, 9] },
  {
    "category": "verduras",
    "pages": [1, 2, 3, 4, 5, 6, 7, 8, 9, 10, 11, 12, 13, 14, 15, 16, 17]
  },
  { "category": "salsas", "pages": [1, 2, 3, 4, 5, 6, 7, 8, 9] },
  { "category": "masas-panes", "pages": [1, 2, 3, 4, 5, 6] },
  { "category": "cremas", "pages": [1, 2, 3, 4, 5, 6, 7] },
  { "category": "patatas-huevos-tortillas", "pages": [1, 2, 3, 4, 5, 6, 7, 8] },
  {
    "category": "aperitivos-faciles",
    "pages": [
      1, 2, 3, 4, 5, 6, 7, 8, 9, 10, 11, 12, 13, 14, 15, 16, 17, 18, 19, 20, 21,
      22, 23, 24, 25, 26, 27, 28
    ]
  },
  {
    "category": "pescados",
    "pages": [
      1, 2, 3, 4, 5, 6, 7, 8, 9, 10, 11, 12, 13, 14, 15, 16, 17, 18, 19, 20, 21,
      22, 23, 24, 25, 26, 27
    ]
  },
  {
    "category": "recetas-mariscos",
    "pages": [1, 2, 3, 4, 5, 6, 7, 8, 9, 10, 11, 12]
  },
  { "category": "vegetarianas", "pages": [1, 2, 3, 4, 5, 6, 7] },
  {
    "category": "sanas-faciles",
    "pages": [
      1, 2, 3, 4, 5, 6, 7, 8, 9, 10, 11, 12, 13, 14, 15, 16, 17, 18, 19, 20, 21,
      22, 23, 24, 25, 26, 27, 28, 29, 30, 31, 32, 33, 34, 35, 36, 37, 38, 39,
      40, 41, 42, 43, 44, 45, 46, 47, 48, 49, 50, 51, 52, 53, 54, 55, 56, 57,
      58, 59, 60, 61, 62, 63, 64, 65, 66, 67, 68
    ]
  },
  { "category": "orientales", "pages": [1, 2, 3, 4, 5, 6, 7, 8] }
]
